linkstat/__main__.py
linkstat/analyzer.py
linkstat/app.py
linkstat/enums.py
linkstat/reporter.py
linkstat-1.0.2.dist-info/METADATA
linkstat-1.0.2.dist-info/WHEEL
linkstat-1.0.2.dist-info/entry_points.txt
linkstat-1.0.2.dist-info/licenses/LICENSE
linkstat-1.0.2.dist-info/RECORD
