Metadata-Version: 2.4
Name: linkstat
Version: 1.0.2
Summary: Perform connectivity checks on URLs listed in the Markdown
Project-URL: Repository, https://github.com/DogFortune/linkstat
Project-URL: Issues, https://github.com/DogFortune/linkstat/issues
Project-URL: Changelog, https://github.com/DogFortune/linkstat/releases
Author-email: DogFortune <dogfortune.2000@gmail.com>
License-File: LICENSE
Keywords: check,link,url
Classifier: Development Status :: 5 - Production/Stable
Classifier: Intended Audience :: Developers
Classifier: License :: OSI Approved :: MIT License
Classifier: Programming Language :: Python :: 3 :: Only
Classifier: Topic :: Documentation
Classifier: Topic :: Internet
Requires-Python: >=3.10
Requires-Dist: dataclasses-json
